Workbook

Sheet Executive Summary
B2: OneSync — Updated MVP Cost & Runway Estimate
B3: Prepared for IIT Roorkee Funding Discussion — March 2026 (v2: Lean Stack)
B5: KEY PARAMETERS
B6: Exchange Rate | C6: 92 | D6: ₹/USD
B7: Team Model | C7: Solo Founder + AI Companion
B8: Health Data Stack | C8: Health Connect + ROOK (free) + Direct SDKs
B9: AI Model Strategy | C9: Mixed routing (see Model Costs tab)
B10: MVP Duration | C10: 3 | D10: months
B12: COST SUMMARY
B13: Category | C13: Cost (₹) | D13: Cost (USD) | E13: Notes
B14: Team & Dev (3 months) | C14: ='Team & Dev'!E12 -> 26040 | D14: ='Team & Dev'!E12/'Executive Summary'!C6 -> 283.04348 | E14: Solo founder + Claude Code + UI freelancer
B15: One-Time Setup | C15: ='Team & Dev'!E20 -> 6600 | D15: ='Team & Dev'!E20/'Executive Summary'!C6 -> 71.73913 | E15: Play Store, API credits, misc
B16: API Testing (3mo, ~10 users) | C16: ='Model Costs'!G14*10*3*'Executive Summary'!C6 -> 12834 | D16: ='Model Costs'!G14*10*3 -> 139.5 | E16: Using cheapest model estimate
B17: Health Data APIs | C17: 0 | D17: 0 | E17: All FREE (Health Connect + ROOK free tier + direct SDKs)
B18: Infrastructure | C18: 0 | D18: 0 | E18: Free tiers: Supabase, Cloudflare, Expo, Vercel
B19: TOTAL MVP COST | C19: =SUM(C14:C18) -> 45474 | D19: =SUM(D14:D18) -> 494.28261
B21: 6-MONTH RUNWAY COST
B22: Total 6-Month Burn | C22: ='6-Month Runway'!I13 -> 115325 | D22: ='6-Month Runway'!I13/'Executive Summary'!C6 -> 1253.5326
B24: Blue cells = editable assumptions. All health data APIs are FREE.

Sheet Model Costs
B2: Single-Model API Cost Comparison
B4: Calls/user/day | C4: 50 | D4: Input tokens/call | E4: 2000 | F4: Output tokens/call | G4: 800
B5: Days/month | C5: 30 | D5: Cache hit rate | E5: 0.5 | F5: Calls/user/mo | G5: =C4*C5 -> 1500
B7: Model | C7: Provider | D7: Input $/MTok | E7: Output $/MTok | F7: Cache $/MTok | G7: Cost/User/Mo | H7: ₹/User/Mo | I7: 100 Users/Mo | J7: ₹ 100 Users/Mo
B8: Claude Opus 4.6 | C8: Anthropic | D8: 5 | E8: 25 | F8: 0.5 | G8: =$G$5*(($E$5*F8+(1-$E$5)*D8)*$E$4+E8*$G$4)/1000000 -> 38.25 | H8: =G8*'Executive Summary'!$C$6 -> 3519 | I8: =G8*100 -> 3825 | J8: =I8*'Executive Summary'!$C$6 -> 351900
B9: Claude Sonnet 4.6 | C9: Anthropic | D9: 3 | E9: 15 | F9: 0.3 | G9: =$G$5*(($E$5*F9+(1-$E$5)*D9)*$E$4+E9*$G$4)/1000000 -> 22.95 | H9: =G9*'Executive Summary'!$C$6 -> 2111.4 | I9: =G9*100 -> 2295 | J9: =I9*'Executive Summary'!$C$6 -> 211140
B10: Claude Haiku 4.5 | C10: Anthropic | D10: 1 | E10: 5 | F10: 0.1 | G10: =$G$5*(($E$5*F10+(1-$E$5)*D10)*$E$4+E10*$G$4)/1000000 -> 7.65 | H10: =G10*'Executive Summary'!$C$6 -> 703.8 | I10: =G10*100 -> 765 | J10: =I10*'Executive Summary'!$C$6 -> 70380
B11: GPT-5.4 | C11: OpenAI | D11: 2.5 | E11: 15 | F11: 0.625 | G11: =$G$5*(($E$5*F11+(1-$E$5)*D11)*$E$4+E11*$G$4)/1000000 -> 22.6875 | H11: =G11*'Executive Summary'!$C$6 -> 2087.25 | I11: =G11*100 -> 2268.75 | J11: =I11*'Executive Summary'!$C$6 -> 208725
B12: GPT-5.2 | C12: OpenAI | D12: 1.75 | E12: 14 | F12: 0.875 | G12: =$G$5*(($E$5*F12+(1-$E$5)*D12)*$E$4+E12*$G$4)/1000000 -> 20.7375 | H12: =G12*'Executive Summary'!$C$6 -> 1907.85 | I12: =G12*100 -> 2073.75 | J12: =I12*'Executive Summary'!$C$6 -> 190785
B13: GPT-4o mini | C13: OpenAI | D13: 0.15 | E13: 0.6 | F13: 0.075 | G13: =$G$5*(($E$5*F13+(1-$E$5)*D13)*$E$4+E13*$G$4)/1000000 -> 1.0575 | H13: =G13*'Executive Summary'!$C$6 -> 97.29 | I13: =G13*100 -> 105.75 | J13: =I13*'Executive Summary'!$C$6 -> 9729
B14: Kimi K2.5 | C14: Moonshot | D14: 0.6 | E14: 3 | F14: 0.1 | G14: =$G$5*(($E$5*F14+(1-$E$5)*D14)*$E$4+E14*$G$4)/1000000 -> 4.65 | H14: =G14*'Executive Summary'!$C$6 -> 427.8 | I14: =G14*100 -> 465 | J14: =I14*'Executive Summary'!$C$6 -> 42780
B15: DeepSeek V3.2 | C15: DeepSeek | D15: 0.28 | E15: 0.42 | F15: 0.028 | G15: =$G$5*(($E$5*F15+(1-$E$5)*D15)*$E$4+E15*$G$4)/1000000 -> 0.966 | H15: =G15*'Executive Summary'!$C$6 -> 88.872 | I15: =G15*100 -> 96.6 | J15: =I15*'Executive Summary'!$C$6 -> 8887.2
B16: Qwen 2.5-72B | C16: Alibaba | D16: 0.12 | E16: 0.39 | F16: 0.06 | G16: =$G$5*(($E$5*F16+(1-$E$5)*D16)*$E$4+E16*$G$4)/1000000 -> 0.738 | H16: =G16*'Executive Summary'!$C$6 -> 67.896 | I16: =G16*100 -> 73.8 | J16: =I16*'Executive Summary'!$C$6 -> 6789.6
B17: GLM-5 | C17: Zhipu AI | D17: 1 | E17: 3.2 | F17: 0.5 | G17: =$G$5*(($E$5*F17+(1-$E$5)*D17)*$E$4+E17*$G$4)/1000000 -> 6.09 | H17: =G17*'Executive Summary'!$C$6 -> 560.28 | I17: =G17*100 -> 609 | J17: =I17*'Executive Summary'!$C$6 -> 56028
B18: MiniMax M2.5 | C18: MiniMax | D18: 0.3 | E18: 1.2 | F18: 0.15 | G18: =$G$5*(($E$5*F18+(1-$E$5)*D18)*$E$4+E18*$G$4)/1000000 -> 2.115 | H18: =G18*'Executive Summary'!$C$6 -> 194.58 | I18: =G18*100 -> 211.5 | J18: =I18*'Executive Summary'!$C$6 -> 19458
B21: YOUR SELECTED MODELS
B22: Model | G22: Cost/User/Mo | H22: ₹/User/Mo | I22: 100 Users/Mo | J22: ₹ 100 Users/Mo
B23: Claude Opus 4.6 | G23: =G8 -> 38.25 | H23: =H8 -> 3519 | I23: =I8 -> 3825 | J23: =J8 -> 351900
B24: Claude Sonnet 4.6 | G24: =G9 -> 22.95 | H24: =H9 -> 2111.4 | I24: =I9 -> 2295 | J24: =J9 -> 211140
B25: GPT-5.4 | G25: =G11 -> 22.6875 | H25: =H11 -> 2087.25 | I25: =I11 -> 2268.75 | J25: =J11 -> 208725
B26: GPT-5.2 | G26: =G12 -> 20.7375 | H26: =H12 -> 1907.85 | I26: =I12 -> 2073.75 | J26: =J12 -> 190785
B27: Kimi K2.5 | G27: =G14 -> 4.65 | H27: =H14 -> 427.8 | I27: =I14 -> 465 | J27: =J14 -> 42780

Sheet Health Data Stack
B2: Health Data Connector Strategy & Costs
B4: LAYER 1: HEALTH CONNECT (Foundation)
B5: Item | C5: Monthly Cost | D5: Annual Cost | E5: Coverage | F5: Notes
B6: Health Connect SDK | C6: Free | D6: Free | E6: All Android devices | F6: On-device, zero latency
B7: Google Fit Bridge | C7: Free | D7: Free | E7: Legacy device fallback | F7: For older companion apps
B9: LAYER 2: ROOK SDK (Enrichment)
B10: Item | C10: Monthly Cost | D10: Annual Cost | E10: Coverage | F10: Notes
B11: ROOK Free Plan | C11: Free | D11: Free | E11: 100+ devices, ≤750 users | F11: Fills HC gaps for WHOOP, Oura, etc.
B12: ROOK Core Plan | C12: $249 | D12: $2,988 | E12: 100+ devices, ≤750 users | F12: Only if >750 users
B14: LAYER 3: DIRECT DEVICE SDKs (Build Over Time)
B15: Device SDK | C15: Cost | D15: Data Access | E15: Build Month | F15: Notes
B16: Samsung Health Data SDK | C16: Free | D16: Full (HRV, SpO2, skin temp) | E16: Month 2 | F16: Partnership application required
B17: Fitbit Web API | C17: Free | D17: Full (intraday needs approval) | E17: Month 3 | F17: OAuth2, rate limits
B18: Garmin Health API | C18: Free | D18: Full (HRV, Body Battery, all) | E18: Month 3 | F18: Business dev application
B19: WHOOP Developer API | C19: Free | D19: Full (strain, recovery, sleep) | E19: Month 4 | F19: App review by WHOOP
B20: Oura API v2 | C20: Free | D20: Full (readiness, HRV, temp) | E20: Month 4 | F20: Standard OAuth2
B21: Apple HealthKit | C21: $99/year | D21: Full (all Apple Watch data) | E21: Month 5 | F21: iOS Phase 2 only
B22: Polar Accesslink API | C22: Free | D22: Good (training, sleep, HR) | E22: Month 6+ | F22: As needed
B24: ALTERNATIVES COMPARISON (Why NOT Terra)
B25: Service | C25: Monthly Cost | D25: Free Tier? | E25: Devices | F25: Verdict
B26: Health Connect + ROOK + SDKs | C26: $0 | D26: Yes (all free) | E26: 10 premium + 100+ via ROOK | F26: ✅ RECOMMENDED
B27: ROOK only | C27: $0-249/mo | D27: Yes (750 users) | E27: 100+ devices | F27: ✅ Good fallback
B28: Sahha.ai | C28: Custom | D28: Sandbox only | E28: 100+ devices | F28: ⚠️ AI scores built-in, limited free
B29: Terra API | C29: $399-499/mo | D29: No | E29: 200+ devices | F29: ❌ Too expensive for MVP
B30: Vital (Junction) | C30: Custom (sales) | D30: No | E30: 300+ devices | F30: ❌ Enterprise-focused
B31: Thryve | C31: Custom (sales) | D31: No | E31: 500+ devices | F31: ❌ Enterprise/insurance focus
B33: TOTAL HEALTH DATA COST (MVP): $0/month

Sheet Team & Dev
B2: Team & Development Costs (Solo Founder Mode)
B4: MVP TEAM (Month 1-3)
B5: Role | C5: Monthly Cost (₹) | D5: Months | E5: Total (₹) | F5: Notes
B6: Solo Founder (You) | C6: 0 | D6: 3 | E6: =C6*D6 -> 0 | F6: Full-stack + AI. No salary during MVP
B7: Co-Founder / Intern | C7: 0 | D7: 3 | E7: =C7*D7 -> 0 | F7: If available from IIT network, equity-only
B8: Claude Code (AI Dev) | C8: 1840 | D8: 3 | E8: =C8*D8 -> 5520 | F8: Claude Max $20/mo × ₹92 = ₹1,840
B9: Cursor Pro (AI IDE) | C9: 1840 | D9: 3 | E9: =C9*D9 -> 5520 | F9: Optional: $20/mo AI-assisted coding
B10: UI/UX Freelancer | C10: 15000 | D10: 1 | E10: =C10*D10 -> 15000 | F10: One-time Figma designs for app + landing
B11: QA / Beta Testers | C11: 0 | D11: 1 | E11: =C11*D11 -> 0 | F11: Free: IIT network, friends, early adopters
B12: TEAM TOTAL | E12: =SUM(E6:E11) -> 26040
B14: ONE-TIME SETUP COSTS
B15: Item | E15: Cost (₹) | F15: Notes
B16: Google Play Developer | E16: 2300 | F16: One-time $25 fee
B17: API Credits (initial testing) | E17: 920 | F17: DeepSeek/Kimi initial calls
B18: Domain + Hosting (annual) | E18: 1380 | F18: ~$15/year via Cloudflare
B19: Miscellaneous | E19: 2000 | F19: Tools, minor expenses
B20: SETUP TOTAL | E20: =SUM(E16:E19) -> 6600

Sheet 6-Month Runway
B2: 6-Month Cash Flow Projection
B4: Item | C4: M1 | D4: M2 | E4: M3 | F4: M4 | G4: M5 | H4: M6 | I4: Cumulative
B5: Team costs (₹) | C5: ='Team & Dev'!E12/3 -> 8680 | D5: ='Team & Dev'!E12/3 -> 8680 | E5: ='Team & Dev'!E12/3 -> 8680 | F5: =1840 -> 1840 | G5: =1840 -> 1840 | H5: =1840 -> 1840
B6: One-time setup (₹) | C6: ='Team & Dev'!E20 -> 6600 | D6: =0 -> 0 | E6: =0 -> 0 | F6: =0 -> 0 | G6: =0 -> 0 | H6: =0 -> 0
B7: API costs (₹) | C7: =0 -> 0 | D7: =0 -> 0 | E7: ='Model Costs'!G14*5*'Executive Summary'!$C$6 -> 2139 | F7: ='Model Costs'!G14*20*'Executive Summary'!$C$6 -> 8556 | G7: ='Model Costs'!G14*50*'Executive Summary'!$C$6 -> 21390 | H7: ='Model Costs'!G14*100*'Executive Summary'!$C$6 -> 42780
B8: Health APIs (₹) | C8: =0 -> 0 | D8: =0 -> 0 | E8: =0 -> 0 | F8: =0 -> 0 | G8: =0 -> 0 | H8: =0 -> 0
B9: Infrastructure (₹) | C9: =0 -> 0 | D9: =0 -> 0 | E9: =0 -> 0 | F9: =0 -> 0 | G9: =0 -> 0 | H9: =25*'Executive Summary'!$C$6 -> 2300
B11: MONTHLY TOTAL (₹) | C11: =SUM(C5:C9) -> 15280 | D11: =SUM(D5:D9) -> 8680 | E11: =SUM(E5:E9) -> 10819 | F11: =SUM(F5:F9) -> 10396 | G11: =SUM(G5:G9) -> 23230 | H11: =SUM(H5:H9) -> 46920
B13: CUMULATIVE TOTAL (₹) | C13: =C11 -> 15280 | D13: =C13+D11 -> 23960 | E13: =D13+E11 -> 34779 | F13: =E13+F11 -> 45175 | G13: =F13+G11 -> 68405 | H13: =G13+H11 -> 115325 | I13: =H13 -> 115325
B15: Users | C15: 0 | D15: 0 | E15: 5 | F15: 20 | G15: 50 | H15: 100
B16: Phase | C16: Build | D16: Build | E16: Build | F16: Beta | G16: Launch | H16: Growth
B18: Note: API costs use Kimi K2.5 ($4.65/user/mo) as baseline.
B19: Actual costs will be lower with mixed model routing.
